{"ocr_results":[{"text":"第四章文革初期軍隧動與穩定的拉锯较量","box":[[356,86],[811,86],[811,109],[356,109]]},{"text":"在小组裡然就是女皇，不什時候、什事都得著她點。”1731966年","box":[[149,206],[1024,206],[1024,236],[149,236]]},{"text":"8月30日，中共中央發布了《中共中央閣於江青代理中央文化革命小组组長","box":[[149,259],[1021,258],[1022,281],[149,282]]},{"text":"務的通知》，通知：“陈伯達同志因病經中央批准休息。在陈伯達同志病假","box":[[152,308],[1020,308],[1020,327],[152,327]]},{"text":"期間或今後離京外出工作期間，他所任的中央文化革命小组组長職務，由第","box":[[153,356],[1019,356],[1019,373],[153,373]]},{"text":"一副組長江青同志代理。”这實際上是毛澤東將文革大權直接交到了江青的手","box":[[152,402],[1019,402],[1019,422],[152,422]]},{"text":"中。文革運勤有了中共中央正式通過的纲领性文件，有了文革小组這個组織","box":[[152,449],[1020,449],[1020,469],[152,469]]},{"text":"機構，也就合理合法地推向全國。","box":[[151,495],[514,496],[514,517],[151,516]]},{"text":"江青然可以號令全國的文革运勤，但是解放軍却是一個獨立的运作系","box":[[204,544],[1020,544],[1020,563],[204,563]]},{"text":"統，它有自己的一套指體系和格的上下级關係。軍像講究的是一切行勤","box":[[152,591],[1020,591],[1020,611],[152,611]]},{"text":"指，全國的野軍和地方部隧统一歸中央軍委直接领導和指。中央文","box":[[150,635],[1022,637],[1021,660],[150,658]]},{"text":"革小组要想在軍内搞類似地方的文革大批判或奪權运勤，就必须在軍内也成","box":[[152,686],[1022,686],[1022,705],[152,705]]},{"text":"立一個相應的機橘，由這個機橘按照江青和中央文革小组的盲意事軍内文","box":[[153,733],[1019,733],[1019,753],[153,753]]},{"text":"革運動。","box":[[152,780],[235,780],[235,801],[152,801]]},{"text":"面對毛澤東發動這場文革運勤，解放軍自然不能置身事外。《五一六通知》","box":[[205,827],[1016,827],[1016,847],[205,847]]},{"text":"發怖後，軍隧馬上面了下一步怎走的局面。以林彪、葉劍英爲主的軍委","box":[[153,875],[1020,875],[1020,895],[153,895]]},{"text":"领導人的一個基本思路，就是軍咳不能，一定要坠持的领導，軍像不介入","box":[[152,922],[1019,922],[1019,941],[152,941]]},{"text":"地方的文革運動。劉志在請示了葉劍英之後，主持起草了《關於執行中央","box":[[150,966],[1020,967],[1020,990],[150,989]]},{"text":"五月十六日通知的通知》，5月25日以總政治部（66）32號文件下發部像。該","box":[[152,1017],[1022,1017],[1022,1037],[152,1037]]},{"text":"《通知》明確指出，文革運動要在全軍各级委“加强领導”下進行，规定軍","box":[[159,1061],[1022,1062],[1021,1085],[159,1084]]},{"text":"豫的文化革命限於“五界”（《五一六通知》提出要“徹底批判學術界、教育界、","box":[[152,1111],[1014,1111],[1014,1131],[152,1131]]},{"text":"新聞界、文界、出版界的資產臀级反勤思想）。《通知》提出要“著重抓好宣","box":[[152,1159],[1020,1159],[1020,1179],[152,1179]]},{"text":"傅、文化、報刊、院校、出版、科研部门的文化革命”，“在連隧和一般機關乾部","box":[[151,1202],[1020,1202],[1020,1225],[151,1225]]},{"text":"中，著重進行正面教育。”亚且规定：對於要點名批判的，包括報刊上公開批判","box":[[152,1252],[1019,1252],[1019,1272],[152,1272]]},{"text":"和在内部批判，都應經黛委批准，“凡属全軍圍内有影響的人物要經總政黛","box":[[151,1299],[1020,1300],[1020,1320],[151,1319]]},{"text":"委批准”174。《通知》還规定，總政設立全軍文化革命小组和文化革命辨公室，","box":[[148,1339],[1008,1340],[1008,1371],[148,1370]]},{"text":"各大审區、各軍種也要在黛委领導下設立文化革命小组及其辦公室等，各人民","box":[[152,1395],[1020,1395],[1020,1415],[152,1415]]},{"text":"注173穆欣《關於“中央文革小组”的一些情况》载《中共史资料》第69辑，中共薰史出版社，1993年3月，","box":[[151,1513],[1013,1513],[1013,1533],[151,1533]]},{"text":"第65。","box":[[151,1542],[226,1542],[226,1562],[151,1562]]},{"text":"注174劉志坠《風雨征程》，國防大學出版社，1996年版，第242页。","box":[[150,1568],[747,1569],[747,1592],[150,1591]]},{"text":"101","box":[[987,1642],[1023,1642],[1023,1666],[987,1666]]}],"dimensions":{"height":1746,"width":1135}}