{"ocr_results":[{"text":"第五章文革前期解放軍與錯综複雜的地方關係","box":[[344,86],[824,86],[824,109],[344,109]]},{"text":"權一事亚無任何具體述，林彪在谈話中反而特别谈了革命舆生產的關傢問","box":[[152,213],[1019,213],[1019,233],[152,233]]},{"text":"题，林彪：“支援地方，總的方面還是抓革命，促生產。不要只抓革命，不促","box":[[151,259],[1022,259],[1022,282],[151,282]]},{"text":"生産了，把生産停顿下來。也不要只搞生産，把革命停頓下來。我們應該同","box":[[152,308],[1020,308],[1020,327],[152,327]]},{"text":"時進行，而且應該以革命來带頭，來挂師，來促進生產。·.生產是不能放","box":[[150,353],[1022,353],[1022,376],[150,376]]},{"text":"的，生產放疑了，會發生非常大的危，會轉過來破壤革命。因此，我的看法，","box":[[151,402],[1005,402],[1005,422],[151,422]]},{"text":"在這個問题上就重要性來，要把革命在第一位，可是就時間上來，生產","box":[[152,449],[1020,449],[1020,469],[152,469]]},{"text":"時間應該估得多。”323由此可以看出，即使林彪支持、護毛澤東的文革略","box":[[151,493],[1020,493],[1020,517],[151,517]]},{"text":"部署，但仍然有自已的見解，尤其表現在强調抓革命的同時還不忘重視生産建","box":[[152,544],[1020,544],[1020,563],[152,563]]},{"text":"設，甚至强調“生産時間應該占得多”。","box":[[151,590],[573,589],[573,610],[151,611]]},{"text":"随著3月19日軍委《决定》的颁發，解放軍参舆“三支兩軍”的任務開始","box":[[204,637],[1022,637],[1022,660],[204,660]]},{"text":"在全軍正式展開。1967年4月3日，中央軍委常委會决定中央軍委設立三","box":[[150,684],[1022,685],[1021,707],[150,706]]},{"text":"固辦公室，即支左辦公室、支工支晨瓣公室、軍管瓣公室。軍工作由總参和","box":[[152,732],[1019,732],[1019,752],[152,752]]},{"text":"總政分管，不另設辦公室。支左瓣公室由華直接舆中央文革繁，支工支","box":[[151,779],[1020,780],[1020,801],[151,800]]},{"text":"震辦公室由杨成武、邱會作等負袁，軍管工作瓣公室由葉劍英主持，亚吸收","box":[[153,827],[1019,827],[1019,847],[153,847]]},{"text":"参和總政及审委辦公的負责幹部参加。各辦公室的任務是瞭解情况，研究","box":[[152,875],[1022,875],[1022,895],[152,895]]},{"text":"問题，亚負向中共中央、中央文革、中央軍委反映情况，提出建，瓣理中共","box":[[150,921],[1020,920],[1020,942],[150,943]]},{"text":"中央、中央文革、中央軍委交瓣的有事填。按照中央軍委的指示和规定，全","box":[[153,969],[1020,969],[1020,989],[153,989]]},{"text":"軍師以上機閣設立“三支雨軍”指部或瓣公室，列人编制。324","box":[[148,1012],[850,1005],[850,1039],[148,1046]]},{"text":"“支工”即支援工業生産，“支農”则是支援震業生産。文革開始後，由","box":[[217,1060],[1021,1062],[1020,1085],[217,1083]]},{"text":"於各地紅衛兵“大民主”、“大串聯”，無政府主義思潮在全國泛，工晨業生","box":[[151,1109],[1020,1109],[1020,1132],[151,1132]]},{"text":"産受到重影響。爲了制止这種現象蔓延，1967年3月3日，毛澤東在潘阳","box":[[152,1158],[1018,1158],[1018,1178],[152,1178]]},{"text":"审區的一份報告上批示：“軍隧不但要協同地方管震業，對工業也要管。陽","box":[[152,1204],[1020,1204],[1020,1227],[152,1227]]},{"text":"重區派遣大批人真進廠做宣傅和做調查的辦法是很好的。二十七軍在無、","box":[[153,1253],[1007,1253],[1007,1273],[153,1273]]},{"text":"五十四軍在重、二十三軍在伊春、章河等處也有好的經。之，軍像不能","box":[[153,1301],[1019,1301],[1019,1320],[153,1320]]},{"text":"坐視工業生産下降而置之不理。”325","box":[[148,1343],[554,1335],[555,1369],[148,1377]]},{"text":"注323宋永毅主编《中國文化大革命文庫》光盤，香港中文大學中國研究服務中心出版，2010年版。","box":[[149,1452],[1012,1454],[1012,1477],[149,1475]]},{"text":"注324《中國人民解放軍軍史》编寫组《中國人民解放軍军史》第六卷，軍事科學出版社，2011年版，","box":[[149,1483],[1023,1484],[1022,1504],[149,1503]]},{"text":"第21。","box":[[151,1513],[222,1513],[222,1534],[151,1534]]},{"text":"注325中共中央文獻研究室编《建國以来毛澤束文稿》，第十二册，中央文獻出版社，1998年版，第","box":[[149,1541],[1022,1542],[1021,1562],[149,1561]]},{"text":"248。","box":[[150,1570],[211,1570],[211,1592],[150,1592]]},{"text":"169","box":[[987,1642],[1024,1642],[1024,1665],[987,1665]]}],"dimensions":{"height":1746,"width":1135}}