{"ocr_results":[{"text":"解放軍舆文化大革命","box":[[128,88],[425,88],[425,108],[128,108]]},{"text":"機兩派群组織一一機閣革命造反總部和絡總站的代表。周指出，絡","box":[[115,213],[983,213],[983,233],[115,233]]},{"text":"總站造業務督小组的反是錯的，亚宣布，將對鐵道部實行軍事管制。陪","box":[[115,260],[984,260],[984,280],[115,280]]},{"text":"司周恩來接見的，有總参軍務部部長蘇靜（凝任鐵道部軍管會主任），總参軍","box":[[115,308],[983,308],[983,327],[115,327]]},{"text":"事交通部副部長杨（凝任部軍管會副主任），逼是蘇、杨在鐵道部的直次亮","box":[[116,356],[982,356],[982,373],[116,373]]},{"text":"相。35月31日，周恩來接到國務院絡員瓣公室報告：鄭州、徐州、蚌埠、金","box":[[115,402],[983,402],[983,422],[115,422]]},{"text":"華、宣化等鐵路纽站段因兩派武门，炸毁機車，停止作業，致使京廣、津浦、","box":[[115,449],[969,449],[969,469],[115,469]]},{"text":"龍海、浙赣等四條主要鐵路韩綫均处於痪狀熊，优徐州一处就停開貨車69","box":[[115,496],[983,496],[983,516],[115,516]]},{"text":"列。周恩來当即批示同意湾南軍區68軍黛委常委關於要求對徐州鐵路分局","box":[[115,544],[983,544],[983,563],[115,563]]},{"text":"和火重站實行軍管的急電。中午，周到毛澤東處，明鐵路輪船關傢到全國交","box":[[115,591],[983,591],[983,611],[115,611]]},{"text":"通命赈，一旦中，國民經濟局勢不可收拾，對鐵路、交通實行軍管的問题不可","box":[[115,637],[982,638],[982,659],[115,658]]},{"text":"再拖。毛澤東表示同意。387","box":[[110,682],[425,673],[426,707],[111,716]]},{"text":"周恩來繁急召集李富春、李先念、葉劍英、萧華、杨成武、谷牧、余秋里開","box":[[167,733],[982,733],[982,753],[167,753]]},{"text":"會，商定了對鐵路交通實行軍管的具體措施：1、快公開發布關於不許中鐵","box":[[115,779],[984,779],[984,802],[115,802]]},{"text":"路輸船交通運输的命令；2、将全國18個鐵路局分给附近驻軍實行軍管包乾，","box":[[115,827],[967,827],[967,847],[115,847]]},{"text":"将沿海沿江輪船交给海軍實行軍管包乾；3、参加軍管的軍咳均舆當地軍分區、","box":[[116,875],[969,875],[969,895],[116,895]]},{"text":"武装部分；4、成總参谋部負凝定調動部隧的計劃，次日拿出方案。388","box":[[109,917],[957,911],[958,944],[110,950]]},{"text":"6月1日，中共中央、國務院、中央軍委、中央文革小组合發出《關於坠","box":[[165,969],[981,969],[981,989],[165,989]]},{"text":"决维護鐵路交通運输革命秩序的命令》。命令指出：","box":[[114,1015],[690,1016],[690,1037],[113,1036]]},{"text":"（一）鐵路，交通運輸部门的廣大革命職工必高翠毛澤东思想偉大红旗，突","box":[[176,1062],[983,1062],[983,1085],[176,1085]]},{"text":"出政治，狠抓革命，猛促生産，守生産岗位，努力做好工作，格遵守動紀律，","box":[[116,1108],[968,1110],[968,1133],[116,1131]]},{"text":"切實保證交通連输的暢通，完成和超额完成連輸计劃，向一切消極总工，影響連","box":[[115,1157],[981,1158],[981,1179],[115,1178]]},{"text":"輸秩序甚至中交通連輸的行為作坚决的门争。","box":[[115,1205],[606,1205],[606,1225],[115,1225]]},{"text":"（二）禁破鐵路，交通設施和國家财産，任何人都不准以任何藉口無票强","box":[[176,1253],[982,1253],[982,1273],[176,1273]]},{"text":"行乘坐車船，不准扒乘貨車和截列車、汽車、輪船，不准妨凝鐵路、交通部门工作","box":[[116,1300],[982,1300],[982,1319],[116,1319]]},{"text":"人員的正常工作，不准武门，不准以卧軌等手段限制車通行。今後凡探用扒車、","box":[[115,1345],[971,1345],[971,1368],[115,1368]]},{"text":"截車及其他不正当的手段來京上的人員，中央概不接見。","box":[[115,1393],[720,1393],[720,1416],[115,1416]]},{"text":"（三）煽動武门，破鐵路、交通運輸秩序和砸毁鐵路、交通設施、連输工具","box":[[175,1439],[982,1440],[982,1463],[175,1462]]},{"text":"注386余汝信《1967：军隧介入鐵路系统過程述略》，载《華夏文摘》增刊，第580期，2007年6月7日。","box":[[113,1511],[979,1512],[979,1535],[112,1534]]},{"text":"注387中共中央文獻研究室编《周恩来年譜1949-1976》，下卷，中央文獻出版社，1997年版，第158页。。","box":[[111,1540],[979,1541],[979,1563],[111,1562]]},{"text":"注388陳揚勇《苦撑危局一周恩来在1967》，重慶出版社，2006年版，第101页。","box":[[114,1569],[799,1570],[799,1591],[113,1590]]},{"text":"204","box":[[110,1645],[151,1645],[151,1668],[110,1668]]}],"dimensions":{"height":1746,"width":1135}}