{"ocr_results":[{"text":"第六章文革中的軍委辦事組","box":[[441,86],[727,86],[727,109],[441,109]]},{"text":"毛主席要我把《解放軍報》管起來，這是實打實的子，子實在不輕。可我","box":[[152,213],[1022,213],[1022,233],[152,233]]},{"text":"再不能推了一一也得知毛、林亚没有放弃要我當總政副主任的想法，還凝","box":[[150,259],[1022,258],[1023,281],[150,282]]},{"text":"經過一個過渡，要我去做總政副主任一一當然這也没有對我明。管《解放","box":[[150,305],[1022,306],[1021,328],[150,327]]},{"text":"审報》，我只是管版面的重大新聞，蕃社、之類，不管報社的運動，","box":[[152,355],[1020,355],[1020,375],[152,375]]},{"text":"管軍報以來我一次也没有到解放軍報社去過。.後來‘三軍”掀起反萧浪潮，","box":[[151,400],[1010,400],[1010,423],[151,423]]},{"text":"大概三軍’看到我不實隙支持他們，所以就我偏萧華、保萧華了。7月份","box":[[152,449],[1009,449],[1009,469],[152,469]]},{"text":"萧華倒了，我也倒了。”614","box":[[146,492],[428,482],[429,517],[148,527]]},{"text":"針對關锋是否被任命為總政副主任一事，江青原秘書圖長爲：“我的","box":[[204,544],[1020,544],[1020,563],[204,563]]},{"text":"印象是：有任命，但他未到。”“文革中和文革後我都問過關锋這件事。文","box":[[151,588],[1020,588],[1020,611],[151,611]]},{"text":"革中，關锋跟我：去當總政副主任，我能力不行，更重要的華是主任，在過","box":[[153,638],[1019,638],[1019,658],[153,658]]},{"text":"去他曾是我的上级，我對他印象不錯，去了不好開展工作。文革後，我問他，","box":[[153,686],[1005,686],[1005,705],[153,705]]},{"text":"總政副主任你没到，是不是主席不同意你去？他：‘不！’主席了：‘我寧","box":[[151,731],[1022,731],[1022,754],[151,754]]},{"text":"可不要《紅旗》，也要軍隧。’”曾任中央文革小组辦事組组長的王廣宇：“時","box":[[151,779],[1022,779],[1022,802],[151,802]]},{"text":"间記不太清楚了，大約是1966年末或1967年初，我在中央文革瓣公室的值","box":[[152,827],[1020,827],[1020,847],[152,847]]},{"text":"班室看到一個文件，是關於任命關锋爲總政治部副主任的文件；發文單位好像","box":[[152,875],[1019,875],[1019,895],[152,895]]},{"text":"是軍委或總政治部，可能是在同一文件中還列了一個總政治部副主任的排序","box":[[153,922],[1020,922],[1020,941],[153,941]]},{"text":"名單，锋排在位副主任的中間位置。”615","box":[[148,964],[650,957],[651,991],[148,998]]},{"text":"邱會作回憶為我們揭開了谜底，邱回憶：“1966年底，江青推中央文","box":[[203,1015],[1021,1015],[1021,1038],[203,1038]]},{"text":"革成員關锋任總政副主任，林彪點頭了，軍委命令備下發。江青看辦成了，","box":[[150,1061],[1006,1062],[1006,1085],[150,1084]]},{"text":"高興地，·關锋到軍隧去，是打先锋的，别被出來就行，以後還有人跟著","box":[[152,1111],[1019,1111],[1019,1131],[152,1131]]},{"text":"去。’江青話時没注意葉群在场。林彪知道後交代，關锋的任命下來，然","box":[[152,1158],[1019,1158],[1019,1178],[152,1178]]},{"text":"後拖著不辨，直到作。”616","box":[[149,1203],[485,1199],[486,1225],[149,1229]]},{"text":"換句話，對於閣锋到總政出任副主任，林彪曾","box":[[471,1202],[1019,1203],[1019,1226],[471,1225]]},{"text":"有一纸任命，但亚無對外正式宣布該令，關锋自然也没到。林彪為何將","box":[[152,1253],[1019,1253],[1019,1273],[152,1273]]},{"text":"锋的任命下來，拖著不瓣直到作？原因無它，就是不充許江青的代理人把","box":[[152,1299],[1018,1299],[1018,1318],[152,1318]]},{"text":"手伸進軍隧狸面來，尤其是不能控制解放軍總政治部這個重要的部门。","box":[[152,1347],[936,1347],[936,1367],[152,1367]]},{"text":"林彪阻正張春稿出任總政主任则更加清楚明白。1970年春，江青對葉群","box":[[205,1395],[1020,1395],[1020,1415],[205,1415]]},{"text":"注614余汝信《關锋當过總政副主任？》，载《枫革園》第424期，2003年11月14日，還见“林彪·","box":[[151,1484],[1015,1484],[1015,1504],[151,1504]]},{"text":"軍隧·文革”網站，www.linbiao.org《余汝信文集》","box":[[152,1512],[597,1512],[597,1532],[152,1532]]},{"text":"615閣長貴《關锋是否被任命过總政副主任？》，载《記憶》第35期，2009年10月30日。","box":[[151,1542],[931,1542],[931,1561],[151,1561]]},{"text":"注616程光《心霍的對話一邱會作舆兒子谈文化大革命》，上册，香港北星出版社，2011年版，第402页。","box":[[149,1568],[1016,1569],[1016,1592],[149,1591]]},{"text":"309","box":[[983,1642],[1024,1642],[1024,1665],[983,1665]]}],"dimensions":{"height":1746,"width":1135}}