{"ocr_results":[{"text":"第十章軍隧的“批林整風”和“四人”的上位","box":[[347,86],[819,86],[819,109],[347,109]]},{"text":"批政治局不政，軍委不軍也不政。毛主席這些指示，適用於政、軍、","box":[[150,210],[1008,211],[1008,234],[150,233]]},{"text":"學，東南西北各個地方，就是告我們要抓大事，值得同志們。今後出修","box":[[151,259],[1020,259],[1020,282],[151,282]]},{"text":"正主義，還是在上層建领域。”934","box":[[149,305],[574,301],[575,327],[149,331]]},{"text":"《元旦獻》舆王洪文的報告中的“批林","box":[[561,305],[1021,306],[1020,328],[561,327]]},{"text":"批孔”不過就是一個幌子，真實的自的還是針對周恩來。","box":[[152,355],[765,355],[765,375],[152,375]]},{"text":"在這場批林批孔運動中，軍隧一直是文革極左派們注的主要目標之一，","box":[[203,399],[1005,401],[1005,425],[203,423]]},{"text":"王洪文、张春等人然在軍中有了一席之地，但仍然是有名無實，距離真正","box":[[153,449],[1019,449],[1019,469],[153,469]]},{"text":"掌控軍的實權還相差甚遠。","box":[[152,497],[476,497],[476,517],[152,517]]},{"text":"1月24日，江青致信王洪文、葉劍英、張春橘和小平，信中：“相當長","box":[[203,543],[1020,542],[1020,564],[203,565]]},{"text":"時間了，許多材料看來，全國圍内的批林整風運勤的發展是很不平衡的，","box":[[152,591],[1004,591],[1004,611],[152,611]]},{"text":"批孔更是深入不下去。而林彪的思想體系舆孔老二的閣係更是不清楚。北","box":[[152,639],[1020,639],[1020,659],[152,659]]},{"text":"京大學，清華大學搞的《林彪舆孔孟之道》是可以助全體同志們解决這個問","box":[[152,686],[1020,686],[1020,705],[152,705]]},{"text":"题。因此，我特請謝静宜和群二同志向全軍指戳員宣讀中央的通知。他们","box":[[152,733],[1022,733],[1022,753],[152,753]]},{"text":"已下過連隧取得經驗，可能對全軍有所助。”935與此同時，江青在1月24日","box":[[150,776],[1022,776],[1022,803],[150,803]]},{"text":"和25日，連續雨天在北京首都體育馆召開中央軍委機閣、京部隧和中共中","box":[[150,826],[1020,825],[1020,848],[150,849]]},{"text":"央直機閣、國家機關萬人批林批孔大會。这兩次會亚非如官方所言是江","box":[[152,875],[1022,875],[1022,895],[152,895]]},{"text":"青擅自召開的，而是毛澤東事先就知道，但未予以制止。9361月24日的會","box":[[151,917],[1023,918],[1022,944],[151,943]]},{"text":"上，中央軍委领導人葉劍英、小平、陳锡出席會，還有京部隧14個大","box":[[154,969],[1022,969],[1022,989],[154,989]]},{"text":"單位的韩部戳士1.8萬人。这兩次大會之後，毛澤東批准了王洪文的提，中","box":[[152,1015],[1020,1016],[1020,1037],[152,1036]]},{"text":"央政治局内部成立主管批林批孔運動的七人小组，計有周恩來、王洪文、張春","box":[[151,1061],[1020,1062],[1020,1085],[151,1084]]},{"text":"、江青、姚文元、華國锋、汪東興。除周恩來之外的其他六個人都是上年底","box":[[152,1111],[1020,1111],[1020,1131],[152,1131]]},{"text":"政治局批周會中“助小组”成。这個形勢乎回到了文革初期時的狀","box":[[152,1158],[1020,1158],[1020,1178],[152,1178]]},{"text":"况。","box":[[149,1204],[188,1204],[188,1228],[149,1228]]},{"text":"如何才能把軍隧調勤起來参舆批林批孔运勤，亚在运勤中逐步掌握軍權","box":[[205,1253],[1008,1253],[1008,1273],[205,1273]]},{"text":"這一直是江青等文革極左派处心横虑想要達成的自標。為此，江青利用自己","box":[[152,1301],[1018,1301],[1018,1320],[152,1320]]},{"text":"的特殊地位直接插手軍的批林批孔運勤，播如文革初期時任全軍文革小","box":[[152,1347],[1020,1347],[1020,1367],[152,1367]]},{"text":"组問那樣，開始對軍隧發號施令。","box":[[152,1395],[542,1395],[542,1415],[152,1415]]},{"text":"江青在給毛澤東寫信後的第二天，即1月13日，未經過葉劍英等中央軍","box":[[203,1441],[1020,1440],[1020,1461],[203,1462]]},{"text":"注934宋永毅主编《中国文化大革命文庫》光盤，香港中文大學中國研究服務中心出版，2010年版。","box":[[151,1513],[999,1513],[999,1533],[151,1533]]},{"text":"注935宋永毅主编《中國文化大革命文庫》光盤，香港中文大學中國研究服務中心出版，2010年版。","box":[[149,1540],[999,1541],[999,1563],[149,1562]]},{"text":"注936高文谦《晚年周恩来》，明鏡出版社，2003年版，第493页。","box":[[150,1569],[715,1571],[715,1591],[150,1589]]},{"text":"485","box":[[983,1642],[1024,1642],[1024,1665],[983,1665]]}],"dimensions":{"height":1746,"width":1135}}