{"ocr_results":[{"text":"结束語","box":[[548,87],[618,87],[618,109],[548,109]]},{"text":"意，清洗了軍中大量的被爲是林彪一系的人馬，製造了不少冤假錯案。","box":[[149,210],[1023,211],[1022,234],[149,233]]},{"text":"然這是整體大環境下之使然，但是葉劍英作爲負軍委辦公會的主要負","box":[[152,260],[1020,260],[1020,280],[152,280]]},{"text":"人仍然负有不可推卸的任。","box":[[153,308],[475,308],[475,327],[153,327]]},{"text":"1971年的“九一三事件”到1973年12月小平重返中央高層，参加","box":[[203,353],[1021,353],[1021,376],[203,376]]},{"text":"中央軍委的工作，时間不過雨年多一點。劍英事的主要工作在於揭批","box":[[153,402],[1020,402],[1020,422],[153,422]]},{"text":"所林彪反黛集團的罪行，清查有運的人舆事，按照毛澤東的指示，解放","box":[[152,449],[1020,449],[1020,469],[152,469]]},{"text":"了一批軍咳導幹部，大规模地調整各级軍隧的领導班子。被解放的軍像","box":[[153,497],[1022,497],[1022,517],[153,517]]},{"text":"韩部有政、萧華、瑞卿、杨成武、杨勇、陳再道、蘇振華、劉震、劉志坠、","box":[[152,544],[1005,544],[1005,563],[152,563]]},{"text":"梁必業、秦基偉、廖漢生、鐘漢華、余立金、黄新廷、莫文、王尚榮、傅崇碧","box":[[152,591],[1019,591],[1019,611],[152,611]]},{"text":"等，不少人恢復了工作，重新安排了领導務。另外，中央軍委對總参、總後、","box":[[151,637],[1013,637],[1013,660],[151,660]]},{"text":"空軍、海軍等單位的领導班子進行了重點的調整，以消除所的林彪影響。","box":[[152,686],[995,686],[995,705],[152,705]]},{"text":"官方更多强調的是，葉劍英在此時的主要工作還包括“恢復軍像的優良","box":[[204,733],[1020,733],[1020,753],[204,753]]},{"text":"傅統”，如開展解放軍學全國人民的活動，整頓軍隧的黛组織，加强基層的","box":[[151,778],[1022,779],[1021,802],[151,801]]},{"text":"建設。同時還恢復了正常的軍事訓，初步整顿了國防工業，抓了科研和生","box":[[152,827],[1019,827],[1019,847],[152,847]]},{"text":"童計劃、產品的算量，使得國防尖端武器的研製有了新的突破，如洲際導彈","box":[[152,875],[1019,875],[1019,895],[152,895]]},{"text":"的研發、衛星通訊站的建成，以及核潜交付海軍使用等。","box":[[151,921],[811,921],[811,943],[151,943]]},{"text":"在葉劍英掌軍的这一段中，軍隧舆文革極左派的矛盾依然存在，它业","box":[[204,969],[1020,969],[1020,989],[204,989]]},{"text":"不因爲林彪的倒台而消失。在文革初期劍英就是林彪稳定軍像的最主要","box":[[153,1017],[1019,1017],[1019,1037],[153,1037]]},{"text":"的手，舆江青等文革左派的矛盾是天然的、不可調和的。江青等人希望","box":[[152,1063],[1019,1063],[1019,1083],[152,1083]]},{"text":"在林彪倒台後取到更多的軍權，但是亚不成功，仍然受到葉劍英等人的抵","box":[[152,1111],[1020,1111],[1020,1131],[152,1131]]},{"text":"制。江青然通過批林批孔運動插手軍隧事宜，但是成效甚微。","box":[[151,1156],[879,1156],[879,1179],[151,1179]]},{"text":"（4）登小平段","box":[[213,1250],[387,1250],[387,1274],[213,1274]]},{"text":"1973年底，小平然恢復了中央工作的部分權力，但是亚未實際掌握","box":[[204,1300],[1020,1299],[1020,1319],[204,1320]]},{"text":"审權。直到1975年1月5日，小平才被正式任命爲中央軍委副主席和解","box":[[152,1347],[1020,1347],[1020,1367],[152,1367]]},{"text":"放軍参長。在中共十届二中全會上被選爲黛中央副主席、中央政治局常","box":[[152,1395],[1019,1395],[1019,1415],[152,1415]]},{"text":"委，四属人大之後周恩來病重住院，小平以代總理的身份開始全面主持黛","box":[[151,1441],[1020,1440],[1020,1461],[151,1462]]},{"text":"政日常工作。然劍英是國防部長，續主持中央軍委日常工作，但是","box":[[152,1489],[1020,1489],[1020,1509],[152,1509]]},{"text":"小平在軍内的作用日益顯著。","box":[[152,1535],[475,1535],[475,1558],[152,1558]]},{"text":"533","box":[[983,1642],[1024,1642],[1024,1665],[983,1665]]}],"dimensions":{"height":1746,"width":1135}}